funboost/__init__.py
funboost/__init__old.py
funboost/__main__.py
funboost/constant.py
funboost/funboost_config_deafult.py
funboost/set_frame_config.py
funboost/assist/__init__.py
funboost/assist/celery_helper.py
funboost/assist/dramatiq_helper.py
funboost/assist/faststream_helper.py
funboost/assist/huey_helper.py
funboost/assist/rocketry_helper.py
funboost/assist/rq_helper.py
funboost/assist/rq_windows_worker.py
funboost/assist/taskiq_helper.py
funboost/beggar_version_implementation/beggar_redis_consumer.py
funboost/concurrent_pool/__init__.py
funboost/concurrent_pool/async_helper.py
funboost/concurrent_pool/async_pool_executor.py
funboost/concurrent_pool/base_pool_type.py
funboost/concurrent_pool/bounded_processpoolexcutor_gt_py37.py
funboost/concurrent_pool/bounded_processpoolexcutor_py36.py
funboost/concurrent_pool/bounded_threadpoolexcutor.py
funboost/concurrent_pool/concurrent_pool_with_multi_process.py
funboost/concurrent_pool/custom_evenlet_pool_executor.py
funboost/concurrent_pool/custom_gevent_pool_executor.py
funboost/concurrent_pool/custom_threadpool_executor.py
funboost/concurrent_pool/custom_threadpool_executor000.py
funboost/concurrent_pool/fixed_thread_pool.py
funboost/concurrent_pool/flexible_thread_pool.py
funboost/concurrent_pool/pool_commons.py
funboost/concurrent_pool/single_thread_executor.py
funboost/concurrent_pool/backup/__init__.py
funboost/concurrent_pool/backup/async_pool_executor0223.py
funboost/concurrent_pool/backup/async_pool_executor_back.py
funboost/concurrent_pool/backup/async_pool_executor_janus.py
funboost/concurrent_pool/backup/grok_async_pool.py
funboost/consumers/__init__.py
funboost/consumers/base_consumer.py
funboost/consumers/empty_consumer.py
funboost/consumers/rabbitmq_amqpstorm_consumer.py
funboost/consumers/rabbitmq_pika_consumer.py
funboost/consumers/rabbitmq_pika_consumerv0.py
funboost/consumers/rabbitmq_rabbitpy_consumer.py
funboost/contrib/__init__.py
funboost/contrib/api_publish_msg.py
funboost_wise-49.1.dist-info/licenses/LICENSE
funboost_wise-49.1.dist-info/METADATA
funboost_wise-49.1.dist-info/WHEEL
funboost_wise-49.1.dist-info/entry_points.txt
funboost_wise-49.1.dist-info/top_level.txt
funboost_wise-49.1.dist-info/RECORD
